{
  "version": "1.0",
  "metadata": {
    "created": "2025-11-17T11:52:13.166338",
    "totalSessions": 8,
    "totalMinutes": 285,
    "lastUpdated": "2025-11-24T13:22:29.268627"
  },
  "subjects": {},
  "goals": [],
  "sessions": [
    {
      "id": 18,
      "timestamp": "2025-11-17T11:52:03+00:00",
      "issueUrl": "https://github.com/KijitoraFinch/my-study-log/issues/18",
      "subject": "歴史総合",
      "goalId": "2025-second-semester-mid",
      "duration": 25,
      "content": "整理プリント",
      "tags": [],
      "materials": [],
      "notes": null,
      "difficulty": null,
      "satisfaction": null
    },
    {
      "id": 19,
      "timestamp": "2025-11-20T09:25:02+00:00",
      "issueUrl": "https://github.com/KijitoraFinch/my-study-log/issues/19",
      "subject": "化学基礎/化学",
      "goalId": "2025-first-semester-final",
      "duration": 25,
      "content": "ぱそー",
      "tags": [],
      "materials": [],
      "notes": null,
      "difficulty": null,
      "satisfaction": null
    },
    {
      "id": 20,
      "timestamp": "2025-11-20T11:39:05+00:00",
      "issueUrl": "https://github.com/KijitoraFinch/my-study-log/issues/20",
      "subject": "化学基礎/化学",
      "goalId": "None",
      "duration": 25,
      "content": "ぱそー",
      "tags": [],
      "materials": [],
      "notes": null,
      "difficulty": null,
      "satisfaction": null
    },
    {
      "id": 21,
      "timestamp": "2025-11-22T17:56:20+00:00",
      "issueUrl": "https://github.com/KijitoraFinch/my-study-log/issues/21",
      "subject": "数学I",
      "goalId": "2025-second-semester-mid",
      "duration": 25,
      "content": "デス化学では水が電離しないので酸を薄めまくるとpHが7を超える",
      "tags": [],
      "materials": [],
      "notes": null,
      "difficulty": null,
      "satisfaction": null
    },
    {
      "id": 22,
      "timestamp": "2025-11-24T10:29:48+00:00",
      "issueUrl": "https://github.com/KijitoraFinch/my-study-log/issues/22",
      "subject": "化学基礎/化学",
      "goalId": "2025-second-semester-mid",
      "duration": 50,
      "content": "ぱそー",
      "tags": [],
      "materials": [],
      "notes": null,
      "difficulty": null,
      "satisfaction": null
    },
    {
      "id": 23,
      "timestamp": "2025-11-24T10:30:16+00:00",
      "issueUrl": "https://github.com/KijitoraFinch/my-study-log/issues/23",
      "subject": "地学基礎/地学",
      "goalId": "None",
      "duration": 60,
      "content": "大気とか",
      "tags": [],
      "materials": [],
      "notes": null,
      "difficulty": null,
      "satisfaction": null
    },
    {
      "id": 24,
      "timestamp": "2025-11-24T12:25:46+00:00",
      "issueUrl": "https://github.com/KijitoraFinch/my-study-log/issues/24",
      "subject": "化学基礎/化学",
      "goalId": "2025-first-semester-final",
      "duration": 25,
      "content": "弱酸/弱塩基の塩であることは酸性/塩基性塩であることの必要条件でも十分条件でもない←ワオ",
      "tags": [],
      "materials": [],
      "notes": null,
      "difficulty": null,
      "satisfaction": null
    },
    {
      "id": 25,
      "timestamp": "2025-11-24T13:22:15+00:00",
      "issueUrl": "https://github.com/KijitoraFinch/my-study-log/issues/25",
      "subject": "化学基礎/化学",
      "goalId": "None",
      "duration": 50,
      "content": "疲れた",
      "tags": [],
      "materials": [],
      "notes": null,
      "difficulty": null,
      "satisfaction": null
    }
  ],
  "config": {},
  "achievements": [],
  "analytics": {
    "weeklyMinutes": [
      185,
      0,
      0,
      0,
      0,
      0,
      0
    ]
  }
}